{
  "session": "令和元年第3回定例会",
  "sourceUrls": [
    "https://www.city.kiryu.lg.jp/shigikai/honkaigi/gian/giketsu/1014964/1015766.html"
  ],
  "scrapedAt": "2026-02-15T21:15:55.611Z",
  "dates": [
    "令和元年8月28日",
    "令和元年9月20日"
  ],
  "bills": [
    {
      "number": "議案第60号",
      "title": "副市長の選任につき同意を求めることについて",
      "result": "同意",
      "category": "市長提出議案"
    },
    {
      "number": "議案第45号",
      "title": "職員の分限に関する条例の一部を改正する条例案",
      "result": "原案可決",
      "category": "市長提出議案"
    },
    {
      "number": "議案第46号",
      "title": "一般職の職員の給与に関する条例の一部を改正する条例案",
      "result": "原案可決",
      "category": "市長提出議案"
    },
    {
      "number": "議案第47号",
      "title": "桐生市職員退職手当支給条例の一部を改正する条例案",
      "result": "原案可決",
      "category": "市長提出議案"
    },
    {
      "number": "議案第48号",
      "title": "桐生市消防団条例の一部を改正する条例案",
      "result": "原案可決",
      "category": "市長提出議案"
    },
    {
      "number": "議案第49号",
      "title": "桐生市市税条例等の一部を改正する条例案",
      "result": "原案可決",
      "category": "市長提出議案"
    },
    {
      "number": "議案第50号",
      "title": "桐生市市営住宅条例の一部を改正する条例案",
      "result": "原案可決",
      "category": "市長提出議案"
    },
    {
      "number": "議案第51号",
      "title": "桐生市下水道条例の一部を改正する条例案",
      "result": "原案可決",
      "category": "市長提出議案"
    },
    {
      "number": "議案第52号",
      "title": "桐生市水道事業給水条例の一部を改正する条例案",
      "result": "原案可決",
      "category": "市長提出議案"
    },
    {
      "number": "議案第53号",
      "title": "桐生消防署東分署建設建築主体工事請負契約の締結について",
      "result": "原案可決",
      "category": "市長提出議案"
    },
    {
      "number": "議案第54号",
      "title": "桐生市印鑑条例の一部を改正する条例案",
      "result": "原案可決",
      "category": "市長提出議案"
    },
    {
      "number": "議案第55号",
      "title": "令和元年度桐生市一般会計補正予算（第2号）",
      "result": "原案可決",
      "category": "市長提出議案"
    },
    {
      "number": "議案第56号",
      "title": "令和元年度桐生市介護保険事業特別会計補正予算（第2号）",
      "result": "原案可決",
      "category": "市長提出議案"
    },
    {
      "number": "議案第57号",
      "title": "平成30年度桐生市歳入歳出決算の認定について",
      "result": "認定",
      "category": "市長提出議案"
    },
    {
      "number": "議案第58号",
      "title": "平成30年度桐生市水道事業会計未処分利益剰余金の処分について",
      "result": "原案可決",
      "category": "市長提出議案"
    },
    {
      "number": "議案第59号",
      "title": "平成30年度桐生市水道事業会計決算の認定について",
      "result": "認定",
      "category": "市長提出議案"
    },
    {
      "number": "議案第61号",
      "title": "令和元年度桐生市一般会計補正予算（第3号）",
      "result": "原案可決",
      "category": "市長提出議案"
    },
    {
      "number": "議案第62号",
      "title": "教育委員会委員の任命につき同意を求めることについて",
      "result": "同意",
      "category": "市長提出議案"
    },
    {
      "number": "議第8号議案",
      "title": "地方財政の充実・強化を求める意見書",
      "result": "原案可決",
      "category": "委員会・議員提出議案"
    },
    {
      "number": "第1号",
      "title": "「『核兵器禁止条約の署名・批准を求める』意見書」を政府にあげる事の採択を求める請願",
      "result": "閉会中の継続審査",
      "category": "請願"
    }
  ],
  "votingRecordPdfUrl": "https://www.city.kiryu.lg.jp/_res/projects/default_project/_page_/001/015/766/kokosannpi1.3.pdf"
}
