{
  "session": "令和6年第1回定例会",
  "sessionSlug": "r6-1-teireikai",
  "sourceUrl": "https://www.city.kiryu.lg.jp/shigikai/honkaigi/shitsusmon/1023677.html",
  "pdfUrl": "https://www.city.kiryu.lg.jp/_res/projects/default_project/_page_/001/023/677/r6t1.ippanshitsumon.pdf",
  "scrapedAt": "2026-02-26T01:12:06.363Z",
  "questions": [
    {
      "memberName": "周藤雅彦",
      "order": 1,
      "items": [
        {
          "title": "災害時の対策と対応 1 阪神淡路大震災・東日本大震災・能登半島地震からの教訓 市長",
          "details": [
            "災害時に住民が必要としたもの",
            "行政における災害時対応の準備"
          ]
        },
        {
          "title": "武道館建設",
          "details": [
            "学校教育からみた武道についての考え",
            "武道館建設の市長の考え"
          ]
        }
      ]
    },
    {
      "memberName": "小島強",
      "order": 2,
      "items": [
        {
          "title": "買い物支援について",
          "details": [
            "現在における買い物弱者への支援状況について",
            "今後の買い物弱者への支援について",
            "配達・移動販売支援の無料化について"
          ]
        },
        {
          "title": "鉛の危険性について",
          "details": [
            "桐生市の土壌における鉛調査の現状について",
            "桐生市の鉛製給水管の状況について現在と今後の予定",
            "公共施設や古い建物の水質検査状況について",
            "きりゅう暮らし応援事業の補助対象について"
          ]
        }
      ]
    },
    {
      "memberName": "飯島英規",
      "order": 3,
      "items": [
        {
          "title": "生存権侵害（生活保護業務不適切対応）について",
          "details": [
            "申請の場面における生存権侵害ではないか。2015年7月事案（記録なし）「男性は、市営住宅において、ライフラインは全て止められ、石油ストーブの燃焼筒に外で拾い集めた木くずを入れてマッチで着火し、わずかに残ったコメを煮炊きしていた。料理人として働いていたが、心臓疾患、体調悪化、就労困難状態が続いていた。」について",
            "執行の場面における生存権侵害ではないか。2023年8月事案（記録あり）「男性は、8月18日から保護費を受給していたが、桐生市は、この男性に対し、支給開始日から生活扶助費を1日1，000円ずつ窓口で手渡して支給していた。本来支給される生活扶助費は、月額約7万円であるが、1日1，000円ずつ支給される生活扶助費では、1カ月で3万円程度にしかならず、生活保護法が規定する生活扶助費を大きく下回っていた。」について",
            "刑法上の犯罪行為（文書偽造罪）ではないか。2023年",
            "月事案（記録あり）「受給者から9月分保護費の受領印を押していないことの申し出があった。桐生市は、本人から受領印をもらわず、福祉課に保管してあった認印を受領簿に押していたことを認めた。」について",
            "受給者数10年半減問題（2011年度の1，163人から2022年度の547人と半減）。この10年で、生存権の申請権侵害がどの程度行われ、申請に至った後却下・取下げ、辞退、廃止、どのように執行が行われたのか、大規模かつ詳細な調査分析が必要ではないか"
          ]
        }
      ]
    },
    {
      "memberName": "辻正男",
      "order": 4,
      "items": [
        {
          "title": "業務インフラの見直しについて",
          "details": [
            "複合機（コピー、プリンター機能）への変更について   市長",
            "現在使用インクトナーについて"
          ]
        },
        {
          "title": "学校事務のデジタル化について",
          "details": [
            "学校事務のデジタル化について",
            "学校のデジタル化の現状と達成率",
            "これからの課題について",
            "使用しているプリンターについて",
            "リサイクルインクトナーの使用について"
          ]
        }
      ]
    },
    {
      "memberName": "工藤英人",
      "order": 5,
      "items": [
        {
          "title": "再生可能エネルギーについて",
          "details": [
            "桐生市の考え方について",
            "現況について",
            "地熱発電事業者と連携する事について"
          ]
        },
        {
          "title": "新里地区・黒保根地区の地域振興について",
          "details": [
            "新里地区の「地域おこし協力隊」の活動について",
            "黒保根地区の「地域振興」について",
            "両地区での総括について"
          ]
        }
      ]
    },
    {
      "memberName": "渡辺恒",
      "order": 6,
      "items": [
        {
          "title": "桐生市が行ってきた人権侵害の生活保護行政の検証について",
          "details": [
            "年ころからの相談件数、人数、申請数、却下数・率について",
            "ケースワーカーの人員推移と2011年以降の急激な保護開始件数の減少について",
            "これまでの人権侵害、違法性の疑われる、不適切な運用がなぜ行われてきたのかについて"
          ]
        },
        {
          "title": "生存権に関わる下水道事業のウォーターＰＰＰ導入をやめることについて",
          "details": [
            "ウォーターＰＰＰ導入検討の動機について",
            "ウォーターＰＰＰ、民間企業が管理・運営することと、自治体のリスクについて",
            "ウォーターＰＰＰ導入はやめることと、国に対し異議の意見を上げることについて"
          ]
        }
      ]
    },
    {
      "memberName": "田島忠一",
      "order": 7,
      "items": [
        {
          "title": "渡良瀬川流域の水害対策について",
          "details": [
            "カスリーン台風の被害について",
            "渡良瀬川に流入している支川について",
            "渡良瀬川と桐生川の令和元年台風19号による被害について",
            "令和元年台風19号後の新たな水害対策について"
          ]
        },
        {
          "title": "渡良瀬川昭和橋上流の河川工事について",
          "details": [
            "渡良瀬川右岸河川工事の概要について",
            "工事完了後の県道332号線について",
            "県道と堤防について"
          ]
        },
        {
          "title": "昭和橋について   1 昭和橋について",
          "details": [
            "足利市の渡良瀬川に架かる中橋について",
            "昭和橋の架け替えについて"
          ]
        }
      ]
    },
    {
      "memberName": "園田基博",
      "order": 8,
      "items": [
        {
          "title": "市営住宅の有効活用 1 市営住宅の入居率について",
          "details": [
            "国が示す公営住宅の目的外使用について",
            "公営住宅の地域対応活用について",
            "提案：①ドワンゴ学園の生徒に対するスクーリング学生寮としての活用②技能実習生寮としての活用"
          ]
        },
        {
          "title": "地域のドライバー不足解消",
          "details": [
            "桐生市のタクシー運行状況について",
            "2024年4月に限定解禁されるライドシェアについて"
          ]
        }
      ]
    },
    {
      "memberName": "岡部純朗",
      "order": 9,
      "items": [
        {
          "title": "渡良瀬川、桐生川の河川整備状況について",
          "details": [
            "赤岩橋から錦桜橋まで",
            "中通り大橋から松原橋まで",
            "渡良瀬川と桐生川の合流地区",
            "桐生川の整備状況"
          ]
        },
        {
          "title": "桐生川の堤防未設置箇所について",
          "details": [
            "桐生川の堤防未設置箇所　宿之島橋上流",
            "今後の見通しは"
          ]
        },
        {
          "title": "市の管理施設（学校も含む）樹木の繁茂処理について",
          "details": [
            "街路樹の伐採実績は",
            "地域からの苦情はありますか",
            "学校の高木の処理は"
          ]
        }
      ]
    },
    {
      "memberName": "丹羽孝志",
      "order": 10,
      "items": [
        {
          "title": "「心のサポーター養成事業」への取組について",
          "details": [
            "メンタルヘルスの現状について",
            "メンタルヘルス対策について",
            "「心のサポーター」を養成するための研修の実施について"
          ]
        },
        {
          "title": "「スポーツマンシップ」をまちづくり、人材育成に生かすために",
          "details": [
            "球都桐生プロジェクトの根幹としての「スポーツマンシップ」",
            "提案：職員人材育成への「スポーツマンシッププログラム」の導入"
          ]
        },
        {
          "title": "市民が安心して歩行できる環境づくり",
          "details": [
            "生活道路における歩行者保護対策について",
            "歩行者を守るための対策強化"
          ]
        },
        {
          "title": "災害用トイレトレーラーについて",
          "details": [
            "災害用トイレトレーラーの導入について"
          ]
        }
      ]
    },
    {
      "memberName": "歌代公司",
      "order": 11,
      "items": [
        {
          "title": "今後の災害対応について",
          "details": [
            "群馬県のＳＩＰ4Ｄの参加による影響について",
            "避難が長期間になった際の支援のシミュレーションについて",
            "災害対応でのドローンの活用について"
          ]
        }
      ]
    },
    {
      "memberName": "石渡宏明",
      "order": 12,
      "items": [
        {
          "title": "「要望」や「提案」の取扱いについて",
          "details": [
            "市政根幹をなす各種施策の編成プロセス",
            "より有意義な議論のあり方と、その適宜フィードバック  部長"
          ]
        },
        {
          "title": "「ゆっくりズムのまち桐生」について",
          "details": [
            "宣言に至る経緯と、宣言の主旨",
            "推進にあたっての課題と取組",
            "今後の取組"
          ]
        },
        {
          "title": "「自治組織の現状と課題」について",
          "details": [
            "自治組織の現状と課題",
            "課題解決のために",
            "地域担当職員制度と県内自治体の状況",
            "桐生版地域担当職員制度の導入スケジュール",
            "期待する事と今後の展開",
            "バックアップ体制"
          ]
        }
      ]
    },
    {
      "memberName": "河原井始",
      "order": 13,
      "items": [
        {
          "title": "人口減少",
          "details": [
            "若者の雇用促進に向けた市役所の働き方について（非正規から正規へ）",
            "社会資本の整備について（子育て中の夫婦が柔軟に働ける仕組みの拡充）"
          ]
        },
        {
          "title": "消費者行政",
          "details": [
            "消費生活相談員について",
            "相談案件とその注意点について"
          ]
        },
        {
          "title": "救急医療の逼迫   1 電話相談窓口について",
          "details": []
        }
      ]
    },
    {
      "memberName": "久保田裕一",
      "order": 14,
      "items": [
        {
          "title": "思いやりの設備「ユニバーサルシート」の設置拡大について",
          "details": [
            "ユニバーサルシートの役割と必要性について",
            "設置状況について",
            "移動式ユニバーサルシートについて",
            "桐生市での設置推進について"
          ]
        },
        {
          "title": "桐生市立小中学校の適正規模・適正配置における住民意見の反映について",
          "details": [
            "学校規模等適正化中学校区検討委員会の出席者からの意見について",
            "小中学校の適正規模・適正配置の手法について",
            "地域住民の意見を反映した学校の在り方の選択肢について",
            "公共施設等総合管理計画との関連性について",
            "教育委員会としての想いは"
          ]
        }
      ]
    },
    {
      "memberName": "関口直久",
      "order": 15,
      "items": [
        {
          "title": "旧川内北小の活用とみやま園移転について",
          "details": [
            "旧川内北小のケヤキの木の保存、存続について",
            "工事用道路と周辺住民対策について",
            "今後の説明会の予定について"
          ]
        },
        {
          "title": "生活保護行政の改善について",
          "details": [
            "今回事件として発覚するまで担当部課で職員からの指摘について",
            "ＮＰＯ法人などによる金銭管理の法令根拠と本人への承諾文書と説明について",
            "ＮＰＯ法人などが管理している人数と現金現在高について",
            "国、県からの監査による具体的事例と改善について",
            "市長、副市長までの報告をあげるパイプはどのようになっていたのかについて"
          ]
        },
        {
          "title": "介護保険について  1 現在の基金額と第9期で予定している基金活用額について",
          "details": [
            "第8期の基金取崩し額と積立額について",
            "保険料の引き下げは基金を更に活用すれば市民負担軽減は可能だったのではないか"
          ]
        }
      ]
    },
    {
      "memberName": "近藤芽衣",
      "order": 16,
      "items": [
        {
          "title": "能登半島地震への被災地対応について",
          "details": [
            "人的支援・応急給水活動・緊急消防援助隊における派遣状況",
            "今後のスケジュール",
            "被災地の活動を経験しての学び"
          ]
        }
      ]
    }
  ]
}
